fuzzly_posts/__init__.py
fuzzly_posts/api.py
fuzzly_posts/blocking.py
fuzzly_posts/constants.py
fuzzly_posts/internal.py
fuzzly_posts/models.py
fuzzly_posts/scoring.py
fuzzly_posts-0.2.6.dist-info/LICENSE
fuzzly_posts-0.2.6.dist-info/METADATA
fuzzly_posts-0.2.6.dist-info/WHEEL
fuzzly_posts-0.2.6.dist-info/top_level.txt
fuzzly_posts-0.2.6.dist-info/RECORD
