Metadata-Version: 2.1
Name: fuzzly-posts
Version: 0.2.6
Summary: posts library for fuzz.ly
Home-page: https://github.com/kheina-com/posts
Author: kheina
License: Mozilla Public License 2.0
Requires-Python: >=3.9.*
License-File: LICENSE
Requires-Dist: kh-common[aerospike,auth,logging,sql] (~=0.6.7)
Requires-Dist: fuzzly-configs (~=0.0.4)
Requires-Dist: fuzzly-users (~=0.0.3)
Requires-Dist: gunicorn (~=20.1.0)
Requires-Dist: scipy (~=1.5.2)
Provides-Extra: build
Requires-Dist: wheel (~=0.36.2) ; extra == 'build'
Requires-Dist: twine (~=3.4.1) ; extra == 'build'
Requires-Dist: isort (~=5.8.0) ; extra == 'build'
